spider88_test/__init__.py
yuanbian_spider_tools/BrowerDriver.py
yuanbian_spider_tools/SpiderConfig.py
yuanbian_spider_tools/YuanbianWidgets.py
yuanbian_spider_tools/__init__.py
yuanbian_spider_tools/hook_js.py
yuanbian_spider_tools/main.py
yuanbian_spider_tools-0.1.2b1.dist-info/METADATA
yuanbian_spider_tools-0.1.2b1.dist-info/WHEEL
yuanbian_spider_tools-0.1.2b1.dist-info/top_level.txt
yuanbian_spider_tools-0.1.2b1.dist-info/RECORD
